{
  "dataset_revision": "3d86128a09e091d6018b6d26cad27f2739fc2db7",
  "evaluation_time": 3297.9234449863434,
  "kg_co2_emissions": null,
  "mteb_version": "1.15.2",
  "scores": {
    "test": [
      {
        "accuracy": 0.7134960000000001,
        "ap": 0.6539200962879846,
        "ap_weighted": 0.6539200962879846,
        "f1": 0.7102846716358528,
        "f1_weighted": 0.7102846716358527,
        "hf_subset": "default",
        "languages": [
          "eng-Latn"
        ],
        "main_score": 0.7134960000000001,
        "scores_per_experiment": [
          {
            "accuracy": 0.75012,
            "ap": 0.6986600169411765,
            "ap_weighted": 0.6986600169411765,
            "f1": 0.7487064739157763,
            "f1_weighted": 0.7487064739157763
          },
          {
            "accuracy": 0.70212,
            "ap": 0.651060605111133,
            "ap_weighted": 0.651060605111133,
            "f1": 0.6996061267158151,
            "f1_weighted": 0.699606126715815
          },
          {
            "accuracy": 0.71584,
            "ap": 0.6442343127962086,
            "ap_weighted": 0.6442343127962086,
            "f1": 0.7100392559826738,
            "f1_weighted": 0.7100392559826738
          },
          {
            "accuracy": 0.76852,
            "ap": 0.7068917495366266,
            "ap_weighted": 0.7068917495366266,
            "f1": 0.7685169329419547,
            "f1_weighted": 0.7685169329419546
          },
          {
            "accuracy": 0.733,
            "ap": 0.6676041870622788,
            "ap_weighted": 0.6676041870622788,
            "f1": 0.7327405055698248,
            "f1_weighted": 0.7327405055698247
          },
          {
            "accuracy": 0.69532,
            "ap": 0.6460784973093715,
            "ap_weighted": 0.6460784973093715,
            "f1": 0.6918550700045327,
            "f1_weighted": 0.6918550700045327
          },
          {
            "accuracy": 0.65464,
            "ap": 0.6096076560812271,
            "ap_weighted": 0.6096076560812271,
            "f1": 0.6487327733328193,
            "f1_weighted": 0.6487327733328193
          },
          {
            "accuracy": 0.68972,
            "ap": 0.6240623742454728,
            "ap_weighted": 0.6240623742454728,
            "f1": 0.6854671897951605,
            "f1_weighted": 0.6854671897951604
          },
          {
            "accuracy": 0.72048,
            "ap": 0.6464221412409195,
            "ap_weighted": 0.6464221412409195,
            "f1": 0.7119830692074647,
            "f1_weighted": 0.7119830692074646
          },
          {
            "accuracy": 0.7052,
            "ap": 0.6445794225554315,
            "ap_weighted": 0.6445794225554315,
            "f1": 0.7051993188925063,
            "f1_weighted": 0.7051993188925064
          }
        ]
      }
    ]
  },
  "task_name": "ImdbClassification"
}