{
  "dataset_revision": "0fd18e25b25c072e09e0d92ab615fda904d66300",
  "evaluation_time": 5.5844786167144775,
  "kg_co2_emissions": null,
  "mteb_version": "1.15.2",
  "scores": {
    "test": [
      {
        "accuracy": 0.7756168831168831,
        "f1": 0.7657380246906624,
        "f1_weighted": 0.7657380246906627,
        "hf_subset": "default",
        "languages": [
          "eng-Latn"
        ],
        "main_score": 0.7756168831168831,
        "scores_per_experiment": [
          {
            "accuracy": 0.7743506493506493,
            "f1": 0.7636026092052823,
            "f1_weighted": 0.7636026092052826
          },
          {
            "accuracy": 0.7808441558441559,
            "f1": 0.7737945171710733,
            "f1_weighted": 0.7737945171710734
          },
          {
            "accuracy": 0.7892857142857143,
            "f1": 0.7815725383582829,
            "f1_weighted": 0.781572538358283
          },
          {
            "accuracy": 0.7811688311688312,
            "f1": 0.7733371819554623,
            "f1_weighted": 0.7733371819554624
          },
          {
            "accuracy": 0.763961038961039,
            "f1": 0.7505415191432059,
            "f1_weighted": 0.7505415191432059
          },
          {
            "accuracy": 0.7801948051948052,
            "f1": 0.7745516787722095,
            "f1_weighted": 0.7745516787722095
          },
          {
            "accuracy": 0.7662337662337663,
            "f1": 0.7550891571927854,
            "f1_weighted": 0.7550891571927856
          },
          {
            "accuracy": 0.7707792207792208,
            "f1": 0.7599916992571184,
            "f1_weighted": 0.7599916992571186
          },
          {
            "accuracy": 0.7766233766233767,
            "f1": 0.7626047498948959,
            "f1_weighted": 0.762604749894896
          },
          {
            "accuracy": 0.7727272727272727,
            "f1": 0.7622945959563091,
            "f1_weighted": 0.762294595956309
          }
        ]
      }
    ]
  },
  "task_name": "Banking77Classification"
}